{
    "4137705485935858256": {
        "ClientVersion": "5046",
        "ServerVersion": "5046",
        "ProductName": "citadel",
        "appID": "1422450",
        "ServerAppID": "1422460",
        "ToolsAppID": "211",
        "SourceRevision": "9104139",
        "VersionDate": "Aug 10 2024",
        "VersionTime": "15:50:24"
    },
    "2052064259501390934": {
        "ClientVersion": "5048",
        "ServerVersion": "5048",
        "ProductName": "citadel",
        "appID": "1422450",
        "ServerAppID": "1422460",
        "ToolsAppID": "211",
        "SourceRevision": "9108429",
        "VersionDate": "Aug 13 2024",
        "VersionTime": "11:37:57"
    },
    "3523004364007244637": {
        "ClientVersion": "5049",
        "ServerVersion": "5049",
        "ProductName": "citadel",
        "appID": "1422450",
        "ServerAppID": "1422460",
        "ToolsAppID": "211",
        "SourceRevision": "9109476",
        "VersionDate": "Aug 13 2024",
        "VersionTime": "15:25:42"
    },
    "5245739343957219741": {
        "ClientVersion": "5050",
        "ServerVersion": "5050",
        "ProductName": "citadel",
        "appID": "1422450",
        "ServerAppID": "1422460",
        "ToolsAppID": "211",
        "SourceRevision": "9109499",
        "VersionDate": "Aug 13 2024",
        "VersionTime": "15:45:29"
    },
    "5622104336372118232": {
        "ClientVersion": "5059",
        "ServerVersion": "5059",
        "ProductName": "citadel",
        "appID": "1422450",
        "ServerAppID": "1422460",
        "ToolsAppID": "211",
        "SourceRevision": "9116221",
        "VersionDate": "Aug 15 2024",
        "VersionTime": "15:13:19"
    },
    "3459388303402873095": {
        "ClientVersion": "5060",
        "ServerVersion": "5060",
        "ProductName": "citadel",
        "appID": "1422450",
        "ServerAppID": "1422460",
        "ToolsAppID": "211",
        "SourceRevision": "9116424",
        "VersionDate": "Aug 15 2024",
        "VersionTime": "15:45:13"
    },
    "8556181921557365147": {
        "ClientVersion": "5062",
        "ServerVersion": "5062",
        "ProductName": "citadel",
        "appID": "1422450",
        "ServerAppID": "1422460",
        "ToolsAppID": "211",
        "SourceRevision": "9116614",
        "VersionDate": "Aug 15 2024",
        "VersionTime": "16:21:41"
    },
    "3327564633680637033": {
        "ClientVersion": "5063",
        "ServerVersion": "5063",
        "ProductName": "citadel",
        "appID": "1422450",
        "ServerAppID": "1422460",
        "ToolsAppID": "211",
        "SourceRevision": "9116733",
        "VersionDate": "Aug 15 2024",
        "VersionTime": "16:46:59"
    },
    "2009182789299622905": {
        "ClientVersion": "5064",
        "ServerVersion": "5064",
        "ProductName": "citadel",
        "appID": "1422450",
        "ServerAppID": "1422460",
        "ToolsAppID": "211",
        "SourceRevision": "9116837",
        "VersionDate": "Aug 15 2024",
        "VersionTime": "17:05:13"
    },
    "8871066833415302740": {
        "ClientVersion": "5067",
        "ServerVersion": "5067",
        "ProductName": "citadel",
        "appID": "1422450",
        "ServerAppID": "1422460",
        "ToolsAppID": "211",
        "SourceRevision": "9117155",
        "VersionDate": "Aug 15 2024",
        "VersionTime": "18:15:38"
    },
    "688506849131143397": {
        "ClientVersion": "5068",
        "ServerVersion": "5068",
        "ProductName": "citadel",
        "appID": "1422450",
        "ServerAppID": "1422460",
        "ToolsAppID": "211",
        "SourceRevision": "9117196",
        "VersionDate": "Aug 15 2024",
        "VersionTime": "18:27:11"
    },
    "6114907171353913122": {
        "ClientVersion": "5069",
        "ServerVersion": "5069",
        "ProductName": "citadel",
        "appID": "1422450",
        "ServerAppID": "1422460",
        "ToolsAppID": "211",
        "SourceRevision": "9117433",
        "VersionDate": "Aug 15 2024",
        "VersionTime": "20:22:28"
    },
    "6232874204020544416": {
        "ClientVersion": "5071",
        "ServerVersion": "5071",
        "ProductName": "citadel",
        "appID": "1422450",
        "ServerAppID": "1422460",
        "ToolsAppID": "211",
        "SourceRevision": "9117515",
        "VersionDate": "Aug 15 2024",
        "VersionTime": "21:29:31"
    },
    "6976498734576286866": {
        "ClientVersion": "5075",
        "ServerVersion": "5075",
        "ProductName": "citadel",
        "appID": "1422450",
        "ServerAppID": "1422460",
        "ToolsAppID": "211",
        "SourceRevision": "9119460",
        "VersionDate": "Aug 16 2024",
        "VersionTime": "15:22:15"
    },
    "1626343787016578765": {
        "ClientVersion": "5077",
        "ServerVersion": "5077",
        "ProductName": "citadel",
        "appID": "1422450",
        "ServerAppID": "1422460",
        "ToolsAppID": "211",
        "SourceRevision": "9120419",
        "VersionDate": "Aug 16 2024",
        "VersionTime": "18:52:35"
    },
    "2503040320853376063": {
        "ClientVersion": "5078",
        "ServerVersion": "5078",
        "ProductName": "citadel",
        "appID": "1422450",
        "ServerAppID": "1422460",
        "ToolsAppID": "211",
        "SourceRevision": "9120584",
        "VersionDate": "Aug 16 2024",
        "VersionTime": "20:24:34"
    },
    "7132013934227648985": {
        "ClientVersion": "5079",
        "ServerVersion": "5079",
        "ProductName": "citadel",
        "appID": "1422450",
        "ServerAppID": "1422460",
        "ToolsAppID": "211",
        "SourceRevision": "9120628",
        "VersionDate": "Aug 16 2024",
        "VersionTime": "21:02:19"
    },
    "848189372795374541": {
        "ClientVersion": "5080",
        "ServerVersion": "5080",
        "ProductName": "citadel",
        "appID": "1422450",
        "ServerAppID": "1422460",
        "ToolsAppID": "211",
        "SourceRevision": "9120705",
        "VersionDate": "Aug 16 2024",
        "VersionTime": "21:47:55"
    },
    "355714314148622380": {
        "ClientVersion": "5081",
        "ServerVersion": "5081",
        "ProductName": "citadel",
        "appID": "1422450",
        "ServerAppID": "1422460",
        "ToolsAppID": "211",
        "SourceRevision": "9120922",
        "VersionDate": "Aug 17 2024",
        "VersionTime": "08:31:00"
    },
    "2465759802143720877": {
        "ClientVersion": "5083",
        "ServerVersion": "5083",
        "ProductName": "citadel",
        "appID": "1422450",
        "ServerAppID": "1422460",
        "ToolsAppID": "211",
        "SourceRevision": "9121093",
        "VersionDate": "Aug 17 2024",
        "VersionTime": "16:54:18"
    },
    "7335128240951719409": {
        "ClientVersion": "5085",
        "ServerVersion": "5085",
        "ProductName": "citadel",
        "appID": "1422450",
        "ServerAppID": "1422460",
        "ToolsAppID": "211",
        "SourceRevision": "9121185",
        "VersionDate": "Aug 17 2024",
        "VersionTime": "20:40:49"
    },
    "3646032621482237743": {
        "ClientVersion": "5086",
        "ServerVersion": "5086",
        "ProductName": "citadel",
        "appID": "1422450",
        "ServerAppID": "1422460",
        "ToolsAppID": "211",
        "SourceRevision": "9121422",
        "VersionDate": "Aug 18 2024",
        "VersionTime": "22:34:00"
    },
    "5440643463150587731": {
        "ClientVersion": "5087",
        "ServerVersion": "5087",
        "ProductName": "citadel",
        "appID": "1422450",
        "ServerAppID": "1422460",
        "ToolsAppID": "211",
        "SourceRevision": "9122359",
        "VersionDate": "Aug 19 2024",
        "VersionTime": "12:10:16"
    },
    "2978560671395893873": {
        "ClientVersion": "5088",
        "ServerVersion": "5088",
        "ProductName": "citadel",
        "appID": "1422450",
        "ServerAppID": "1422460",
        "ToolsAppID": "211",
        "SourceRevision": "9124617",
        "VersionDate": "Aug 20 2024",
        "VersionTime": "10:44:43"
    },
    "4057390968941286811": {
        "ClientVersion": "5089",
        "ServerVersion": "5089",
        "ProductName": "citadel",
        "appID": "1422450",
        "ServerAppID": "1422460",
        "ToolsAppID": "211",
        "SourceRevision": "9125161",
        "VersionDate": "Aug 20 2024",
        "VersionTime": "12:41:45"
    },
    "6824367596786433824": {
        "ClientVersion": "5090",
        "ServerVersion": "5090",
        "ProductName": "citadel",
        "appID": "1422450",
        "ServerAppID": "1422460",
        "ToolsAppID": "211",
        "SourceRevision": "9133580",
        "VersionDate": "Aug 22 2024",
        "VersionTime": "18:50:00"
    },
    "2791460478218364625": {
        "ClientVersion": "5091",
        "ServerVersion": "5091",
        "ProductName": "citadel",
        "appID": "1422450",
        "ServerAppID": "1422460",
        "ToolsAppID": "211",
        "SourceRevision": "9135663",
        "VersionDate": "Aug 23 2024",
        "VersionTime": "14:53:15"
    },
    "4569320816740649284": {
        "ClientVersion": "5092",
        "ServerVersion": "5092",
        "ProductName": "citadel",
        "appID": "1422450",
        "ServerAppID": "1422460",
        "ToolsAppID": "211",
        "SourceRevision": "9136678",
        "VersionDate": "Aug 24 2024",
        "VersionTime": "07:53:58"
    },
    "7358150729940591778": {
        "ClientVersion": "5093",
        "ServerVersion": "5093",
        "ProductName": "citadel",
        "appID": "1422450",
        "ServerAppID": "1422460",
        "ToolsAppID": "211",
        "SourceRevision": "9136858",
        "VersionDate": "Aug 25 2024",
        "VersionTime": "08:03:36"
    },
    "8498395011617560577": {
        "ClientVersion": "5095",
        "ServerVersion": "5095",
        "ProductName": "citadel",
        "appID": "1422450",
        "ServerAppID": "1422460",
        "ToolsAppID": "211",
        "SourceRevision": "9142363",
        "VersionDate": "Aug 27 2024",
        "VersionTime": "19:03:02"
    },
    "5559171354573942559": {
        "ClientVersion": "5100",
        "ServerVersion": "5100",
        "ProductName": "citadel",
        "appID": "1422450",
        "ServerAppID": "1422460",
        "ToolsAppID": "211",
        "SourceRevision": "9149314",
        "VersionDate": "Aug 29 2024",
        "VersionTime": "16:24:40"
    },
    "7033698435015792100": {
        "ClientVersion": "5102",
        "ServerVersion": "5102",
        "ProductName": "citadel",
        "appID": "1422450",
        "ServerAppID": "1422460",
        "ToolsAppID": "211",
        "SourceRevision": "9149702",
        "VersionDate": "Aug 29 2024",
        "VersionTime": "17:57:39"
    },
    "5039595391771894419": {
        "ClientVersion": "5103",
        "ServerVersion": "5103",
        "ProductName": "citadel",
        "appID": "1422450",
        "ServerAppID": "1422460",
        "ToolsAppID": "211",
        "SourceRevision": "9150082",
        "VersionDate": "Aug 29 2024",
        "VersionTime": "20:06:09"
    },
    "9033814203781938158": {
        "ClientVersion": "5105",
        "ServerVersion": "5105",
        "ProductName": "citadel",
        "appID": "1422450",
        "ServerAppID": "1422460",
        "ToolsAppID": "211",
        "SourceRevision": "9150153",
        "VersionDate": "Aug 29 2024",
        "VersionTime": "20:54:12"
    },
    "3257603223321475634": {
        "ClientVersion": "5106",
        "ServerVersion": "5106",
        "ProductName": "citadel",
        "appID": "1422450",
        "ServerAppID": "1422460",
        "ToolsAppID": "211",
        "SourceRevision": "9150340",
        "VersionDate": "Aug 29 2024",
        "VersionTime": "23:02:44"
    },
    "6280897906387112301": {
        "ClientVersion": "5108",
        "ServerVersion": "5108",
        "ProductName": "citadel",
        "appID": "1422450",
        "ServerAppID": "1422460",
        "ToolsAppID": "211",
        "SourceRevision": "9150696",
        "VersionDate": "Aug 30 2024",
        "VersionTime": "08:34:21"
    },
    "6566634437861796152": {
        "ClientVersion": "5109",
        "ServerVersion": "5109",
        "ProductName": "citadel",
        "appID": "1422450",
        "ServerAppID": "1422460",
        "ToolsAppID": "211",
        "SourceRevision": "9151711",
        "VersionDate": "Aug 30 2024",
        "VersionTime": "13:49:44"
    },
    "7060417893867179414": {
        "ClientVersion": "5111",
        "ServerVersion": "5111",
        "ProductName": "citadel",
        "appID": "1422450",
        "ServerAppID": "1422460",
        "ToolsAppID": "211",
        "SourceRevision": "9152500",
        "VersionDate": "Aug 30 2024",
        "VersionTime": "16:13:10"
    },
    "329343896823211186": {
        "ClientVersion": "5114",
        "ServerVersion": "5114",
        "ProductName": "citadel",
        "appID": "1422450",
        "ServerAppID": "1422460",
        "ToolsAppID": "211",
        "SourceRevision": "9153172",
        "VersionDate": "Aug 30 2024",
        "VersionTime": "20:30:47"
    },
    "8054428535823173454": {
        "ClientVersion": "5115",
        "ServerVersion": "5115",
        "ProductName": "citadel",
        "appID": "1422450",
        "ServerAppID": "1422460",
        "ToolsAppID": "211",
        "SourceRevision": "9153211",
        "VersionDate": "Aug 30 2024",
        "VersionTime": "21:09:58"
    },
    "629665074320775173": {
        "ClientVersion": "5116",
        "ServerVersion": "5116",
        "ProductName": "citadel",
        "appID": "1422450",
        "ServerAppID": "1422460",
        "ToolsAppID": "211",
        "SourceRevision": "9153733",
        "VersionDate": "Aug 31 2024",
        "VersionTime": "18:43:25"
    },
    "5586205941927510163": {
        "ClientVersion": "5118",
        "ServerVersion": "5118",
        "ProductName": "citadel",
        "appID": "1422450",
        "ServerAppID": "1422460",
        "ToolsAppID": "211",
        "SourceRevision": "9154095",
        "VersionDate": "Sep 01 2024",
        "VersionTime": "13:32:19"
    },
    "3171481965223521138": {
        "ClientVersion": "5119",
        "ServerVersion": "5119",
        "ProductName": "citadel",
        "appID": "1422450",
        "ServerAppID": "1422460",
        "ToolsAppID": "211",
        "SourceRevision": "9155187",
        "VersionDate": "Sep 02 2024",
        "VersionTime": "14:56:12"
    },
    "2036639395491743121": {
        "ClientVersion": "5120",
        "ServerVersion": "5120",
        "ProductName": "citadel",
        "appID": "1422450",
        "ServerAppID": "1422460",
        "ToolsAppID": "211",
        "SourceRevision": "9155570",
        "VersionDate": "Sep 02 2024",
        "VersionTime": "19:21:34"
    },
    "1249795951701720724": {
        "ClientVersion": "5121",
        "ServerVersion": "5121",
        "ProductName": "citadel",
        "appID": "1422450",
        "ServerAppID": "1422460",
        "ToolsAppID": "211",
        "SourceRevision": "9162556",
        "VersionDate": "Sep 05 2024",
        "VersionTime": "13:12:03"
    },
    "4265222067702422526": {
        "ClientVersion": "5122",
        "ServerVersion": "5122",
        "ProductName": "citadel",
        "appID": "1422450",
        "ServerAppID": "1422460",
        "ToolsAppID": "211",
        "SourceRevision": "9163006",
        "VersionDate": "Sep 05 2024",
        "VersionTime": "15:28:41"
    },
    "2566941267379712021": {
        "ClientVersion": "5123",
        "ServerVersion": "5123",
        "ProductName": "citadel",
        "appID": "1422450",
        "ServerAppID": "1422460",
        "ToolsAppID": "211",
        "SourceRevision": "9164582",
        "VersionDate": "Sep 05 2024",
        "VersionTime": "23:22:04"
    },
    "35226395596188333": {
        "ClientVersion": "5124",
        "ServerVersion": "5124",
        "ProductName": "citadel",
        "appID": "1422450",
        "ServerAppID": "1422460",
        "ToolsAppID": "211",
        "SourceRevision": "9167961",
        "VersionDate": "Sep 07 2024",
        "VersionTime": "12:49:22"
    },
    "7568379704400122064": {
        "ClientVersion": "5127",
        "ServerVersion": "5127",
        "ProductName": "citadel",
        "appID": "1422450",
        "ServerAppID": "1422460",
        "ToolsAppID": "211",
        "SourceRevision": "9170850",
        "VersionDate": "Sep 09 2024",
        "VersionTime": "15:53:11"
    },
    "7510267314893368986": {
        "ClientVersion": "5129",
        "ServerVersion": "5129",
        "ProductName": "citadel",
        "appID": "1422450",
        "ServerAppID": "1422460",
        "ToolsAppID": "211",
        "SourceRevision": "9171141",
        "VersionDate": "Sep 09 2024",
        "VersionTime": "16:55:48"
    },
    "5888925540418915824": {
        "ClientVersion": "5135",
        "ServerVersion": "5135",
        "ProductName": "citadel",
        "appID": "1422450",
        "ServerAppID": "1422460",
        "ToolsAppID": "211",
        "SourceRevision": "9180170",
        "VersionDate": "Sep 12 2024",
        "VersionTime": "16:31:25"
    },
    "5516777253862139628": {
        "ClientVersion": "5136",
        "ServerVersion": "5136",
        "ProductName": "citadel",
        "appID": "1422450",
        "ServerAppID": "1422460",
        "ToolsAppID": "211",
        "SourceRevision": "9180180",
        "VersionDate": "Sep 12 2024",
        "VersionTime": "17:00:02"
    },
    "8419900641679331698": {
        "ClientVersion": "5138",
        "ServerVersion": "5138",
        "ProductName": "citadel",
        "appID": "1422450",
        "ServerAppID": "1422460",
        "ToolsAppID": "211",
        "SourceRevision": "9180546",
        "VersionDate": "Sep 12 2024",
        "VersionTime": "18:01:55"
    },
    "1682317656415564998": {
        "ClientVersion": "5140",
        "ServerVersion": "5140",
        "ProductName": "citadel",
        "appID": "1422450",
        "ServerAppID": "1422460",
        "ToolsAppID": "211",
        "SourceRevision": "9180723",
        "VersionDate": "Sep 12 2024",
        "VersionTime": "19:06:03"
    },
    "5547986301570402563": {
        "ClientVersion": "5142",
        "ServerVersion": "5142",
        "ProductName": "citadel",
        "appID": "1422450",
        "ServerAppID": "1422460",
        "ToolsAppID": "211",
        "SourceRevision": "9180858",
        "VersionDate": "Sep 12 2024",
        "VersionTime": "20:31:03"
    },
    "4745569323660308943": {
        "ClientVersion": "5143",
        "ServerVersion": "5143",
        "ProductName": "citadel",
        "appID": "1422450",
        "ServerAppID": "1422460",
        "ToolsAppID": "211",
        "SourceRevision": "9181019",
        "VersionDate": "Sep 12 2024",
        "VersionTime": "23:24:35"
    },
    "58357994342504134": {
        "ClientVersion": "5145",
        "ServerVersion": "5145",
        "ProductName": "citadel",
        "appID": "1422450",
        "ServerAppID": "1422460",
        "ToolsAppID": "211",
        "SourceRevision": "9182368",
        "VersionDate": "Sep 13 2024",
        "VersionTime": "12:52:59"
    },
    "2350766867727453047": {
        "ClientVersion": "5151",
        "ServerVersion": "5151",
        "ProductName": "citadel",
        "appID": "1422450",
        "ServerAppID": "1422460",
        "ToolsAppID": "211",
        "SourceRevision": "9183796",
        "VersionDate": "Sep 13 2024",
        "VersionTime": "17:48:47"
    },
    "2853676758991197186": {
        "ClientVersion": "5155",
        "ServerVersion": "5155",
        "ProductName": "citadel",
        "appID": "1422450",
        "ServerAppID": "1422460",
        "ToolsAppID": "211",
        "SourceRevision": "9184070",
        "VersionDate": "Sep 13 2024",
        "VersionTime": "19:45:51"
    },
    "4888465758757129411": {
        "ClientVersion": "5156",
        "ServerVersion": "5156",
        "ProductName": "citadel",
        "appID": "1422450",
        "ServerAppID": "1422460",
        "ToolsAppID": "211",
        "SourceRevision": "9184181",
        "VersionDate": "Sep 13 2024",
        "VersionTime": "21:57:32"
    },
    "3341810551027496497": {
        "ClientVersion": "5157",
        "ServerVersion": "5157",
        "ProductName": "citadel",
        "appID": "1422450",
        "ServerAppID": "1422460",
        "ToolsAppID": "211",
        "SourceRevision": "9184275",
        "VersionDate": "Sep 14 2024",
        "VersionTime": "00:30:06"
    },
    "6841443037131554230": {
        "ClientVersion": "5158",
        "ServerVersion": "5158",
        "ProductName": "citadel",
        "appID": "1422450",
        "ServerAppID": "1422460",
        "ToolsAppID": "211",
        "SourceRevision": "9184340",
        "VersionDate": "Sep 14 2024",
        "VersionTime": "07:51:38"
    },
    "6580131610705564023": {
        "ClientVersion": "5162",
        "ServerVersion": "5162",
        "ProductName": "citadel",
        "appID": "1422450",
        "ServerAppID": "1422460",
        "ToolsAppID": "211",
        "SourceRevision": "9184518",
        "VersionDate": "Sep 14 2024",
        "VersionTime": "13:09:38"
    },
    "409502192204933244": {
        "ClientVersion": "5163",
        "ServerVersion": "5163",
        "ProductName": "citadel",
        "appID": "1422450",
        "ServerAppID": "1422460",
        "ToolsAppID": "211",
        "SourceRevision": "9184682",
        "VersionDate": "Sep 14 2024",
        "VersionTime": "19:26:58"
    },
    "7531966821480206617": {
        "ClientVersion": "5164",
        "ServerVersion": "5164",
        "ProductName": "citadel",
        "appID": "1422450",
        "ServerAppID": "1422460",
        "ToolsAppID": "211",
        "SourceRevision": "9184704",
        "VersionDate": "Sep 14 2024",
        "VersionTime": "21:03:43"
    },
    "212723827960620437": {
        "ClientVersion": "5165",
        "ServerVersion": "5165",
        "ProductName": "citadel",
        "appID": "1422450",
        "ServerAppID": "1422460",
        "ToolsAppID": "211",
        "SourceRevision": "9186488",
        "VersionDate": "Sep 16 2024",
        "VersionTime": "14:26:41"
    },
    "571428258974008041": {
        "ClientVersion": "5169",
        "ServerVersion": "5169",
        "ProductName": "citadel",
        "appID": "1422450",
        "ServerAppID": "1422460",
        "ToolsAppID": "211",
        "SourceRevision": "9189851",
        "VersionDate": "Sep 17 2024",
        "VersionTime": "15:57:20"
    },
    "3931949366150044443": {
        "ClientVersion": "5170",
        "ServerVersion": "5170",
        "ProductName": "citadel",
        "appID": "1422450",
        "ServerAppID": "1422460",
        "ToolsAppID": "211",
        "SourceRevision": "9190730",
        "VersionDate": "Sep 17 2024",
        "VersionTime": "22:37:15"
    },
    "9117824023207771698": {
        "ClientVersion": "5171",
        "ServerVersion": "5171",
        "ProductName": "citadel",
        "appID": "1422450",
        "ServerAppID": "1422460",
        "ToolsAppID": "211",
        "SourceRevision": "9191298",
        "VersionDate": "Sep 18 2024",
        "VersionTime": "10:17:36"
    },
    "7389519204074484302": {
        "ClientVersion": "5172",
        "ServerVersion": "5172",
        "ProductName": "citadel",
        "appID": "1422450",
        "ServerAppID": "1422460",
        "ToolsAppID": "211",
        "SourceRevision": "9194661",
        "VersionDate": "Sep 19 2024",
        "VersionTime": "11:05:46"
    },
    "3362363365023623347": {
        "ClientVersion": "5176",
        "ServerVersion": "5176",
        "ProductName": "citadel",
        "appID": "1422450",
        "ServerAppID": "1422460",
        "ToolsAppID": "211",
        "SourceRevision": "9196222",
        "VersionDate": "Sep 19 2024",
        "VersionTime": "17:50:46"
    },
    "7601212445901204175": {
        "ClientVersion": "5177",
        "ServerVersion": "5177",
        "ProductName": "citadel",
        "appID": "1422450",
        "ServerAppID": "1422460",
        "ToolsAppID": "211",
        "SourceRevision": "9196456",
        "VersionDate": "Sep 19 2024",
        "VersionTime": "19:04:10"
    },
    "1982344895897433968": {
        "ClientVersion": "5178",
        "ServerVersion": "5178",
        "ProductName": "citadel",
        "appID": "1422450",
        "ServerAppID": "1422460",
        "ToolsAppID": "211",
        "SourceRevision": "9196542",
        "VersionDate": "Sep 19 2024",
        "VersionTime": "19:45:14"
    },
    "8828387698301188": {
        "ClientVersion": "5179",
        "ServerVersion": "5179",
        "ProductName": "citadel",
        "appID": "1422450",
        "ServerAppID": "1422460",
        "ToolsAppID": "211",
        "SourceRevision": "9196888",
        "VersionDate": "Sep 20 2024",
        "VersionTime": "02:14:08"
    },
    "6023595993027382382": {
        "ClientVersion": "5180",
        "ServerVersion": "5180",
        "ProductName": "citadel",
        "appID": "1422450",
        "ServerAppID": "1422460",
        "ToolsAppID": "211",
        "SourceRevision": "9197487",
        "VersionDate": "Sep 20 2024",
        "VersionTime": "11:00:17"
    },
    "2797258100636598929": {
        "ClientVersion": "5181",
        "ServerVersion": "5181",
        "ProductName": "citadel",
        "appID": "1422450",
        "ServerAppID": "1422460",
        "ToolsAppID": "211",
        "SourceRevision": "9197982",
        "VersionDate": "Sep 20 2024",
        "VersionTime": "12:31:41"
    },
    "3569122401113766710": {
        "ClientVersion": "5183",
        "ServerVersion": "5183",
        "ProductName": "citadel",
        "appID": "1422450",
        "ServerAppID": "1422460",
        "ToolsAppID": "211",
        "SourceRevision": "9198588",
        "VersionDate": "Sep 20 2024",
        "VersionTime": "14:43:54"
    },
    "443323355425722313": {
        "ClientVersion": "5184",
        "ServerVersion": "5184",
        "ProductName": "citadel",
        "appID": "1422450",
        "ServerAppID": "1422460",
        "ToolsAppID": "211",
        "SourceRevision": "9198963",
        "VersionDate": "Sep 20 2024",
        "VersionTime": "16:14:54"
    },
    "8584134807053004992": {
        "ClientVersion": "5186",
        "ServerVersion": "5186",
        "ProductName": "citadel",
        "appID": "1422450",
        "ServerAppID": "1422460",
        "ToolsAppID": "211",
        "SourceRevision": "9199757",
        "VersionDate": "Sep 21 2024",
        "VersionTime": "00:21:56"
    },
    "8986896931405252599": {
        "ClientVersion": "5187",
        "ServerVersion": "5187",
        "ProductName": "citadel",
        "appID": "1422450",
        "ServerAppID": "1422460",
        "ToolsAppID": "211",
        "SourceRevision": "9200370",
        "VersionDate": "Sep 22 2024",
        "VersionTime": "14:44:35"
    },
    "1743757208636711258": {
        "ClientVersion": "5188",
        "ServerVersion": "5188",
        "ProductName": "citadel",
        "appID": "1422450",
        "ServerAppID": "1422460",
        "ToolsAppID": "211",
        "SourceRevision": "9202292",
        "VersionDate": "Sep 23 2024",
        "VersionTime": "15:59:43"
    },
    "8494661584461021274": {
        "ClientVersion": "5189",
        "ServerVersion": "5189",
        "ProductName": "citadel",
        "appID": "1422450",
        "ServerAppID": "1422460",
        "ToolsAppID": "211",
        "SourceRevision": "9203916",
        "VersionDate": "Sep 24 2024",
        "VersionTime": "09:54:09"
    },
    "1205388541731512720": {
        "ClientVersion": "5190",
        "ServerVersion": "5190",
        "ProductName": "citadel",
        "appID": "1422450",
        "ServerAppID": "1422460",
        "ToolsAppID": "211",
        "SourceRevision": "9204531",
        "VersionDate": "Sep 24 2024",
        "VersionTime": "12:10:52"
    },
    "6754828840051311402": {
        "ClientVersion": "5191",
        "ServerVersion": "5191",
        "ProductName": "citadel",
        "appID": "1422450",
        "ServerAppID": "1422460",
        "ToolsAppID": "211",
        "SourceRevision": "9205402",
        "VersionDate": "Sep 24 2024",
        "VersionTime": "14:51:00"
    },
    "7818537816712071636": {
        "ClientVersion": "5192",
        "ServerVersion": "5192",
        "ProductName": "citadel",
        "appID": "1422450",
        "ServerAppID": "1422460",
        "ToolsAppID": "211",
        "SourceRevision": "9205534",
        "VersionDate": "Sep 24 2024",
        "VersionTime": "15:49:58"
    },
    "8590542750271090269": {
        "ClientVersion": "5193",
        "ServerVersion": "5193",
        "ProductName": "citadel",
        "appID": "1422450",
        "ServerAppID": "1422460",
        "ToolsAppID": "211",
        "SourceRevision": "9208391",
        "VersionDate": "Sep 25 2024",
        "VersionTime": "13:49:57"
    },
    "3921492920368224553": {
        "ClientVersion": "5201",
        "ServerVersion": "5201",
        "ProductName": "citadel",
        "appID": "1422450",
        "ServerAppID": "1422460",
        "ToolsAppID": "211",
        "SourceRevision": "9213271",
        "VersionDate": "Sep 26 2024",
        "VersionTime": "15:27:21"
    },
    "4448944656864615551": {
        "ClientVersion": "5202",
        "ServerVersion": "5202",
        "ProductName": "citadel",
        "appID": "1422450",
        "ServerAppID": "1422460",
        "ToolsAppID": "211",
        "SourceRevision": "9213543",
        "VersionDate": "Sep 26 2024",
        "VersionTime": "15:57:06"
    },
    "4669592844518320676": {
        "ClientVersion": "5203",
        "ServerVersion": "5203",
        "ProductName": "citadel",
        "appID": "1422450",
        "ServerAppID": "1422460",
        "ToolsAppID": "211",
        "SourceRevision": "9213683",
        "VersionDate": "Sep 26 2024",
        "VersionTime": "16:11:38"
    },
    "4338388029934374344": {
        "ClientVersion": "5205",
        "ServerVersion": "5205",
        "ProductName": "citadel",
        "appID": "1422450",
        "ServerAppID": "1422460",
        "ToolsAppID": "211",
        "SourceRevision": "9214067",
        "VersionDate": "Sep 26 2024",
        "VersionTime": "17:08:36"
    },
    "3159422876373397103": {
        "ClientVersion": "5207",
        "ServerVersion": "5207",
        "ProductName": "citadel",
        "appID": "1422450",
        "ServerAppID": "1422460",
        "ToolsAppID": "211",
        "SourceRevision": "9214310",
        "VersionDate": "Sep 26 2024",
        "VersionTime": "17:48:02"
    },
    "7077759894216867799": {
        "ClientVersion": "5208",
        "ServerVersion": "5208",
        "ProductName": "citadel",
        "appID": "1422450",
        "ServerAppID": "1422460",
        "ToolsAppID": "211",
        "SourceRevision": "9214473",
        "VersionDate": "Sep 26 2024",
        "VersionTime": "18:51:54"
    },
    "2669874087483310998": {
        "ClientVersion": "5210",
        "ServerVersion": "5210",
        "ProductName": "citadel",
        "appID": "1422450",
        "ServerAppID": "1422460",
        "ToolsAppID": "211",
        "SourceRevision": "9214635",
        "VersionDate": "Sep 26 2024",
        "VersionTime": "20:25:34"
    },
    "1558264121146302396": {
        "ClientVersion": "5211",
        "ServerVersion": "5211",
        "ProductName": "citadel",
        "appID": "1422450",
        "ServerAppID": "1422460",
        "ToolsAppID": "211",
        "SourceRevision": "9214810",
        "VersionDate": "Sep 26 2024",
        "VersionTime": "22:39:53"
    },
    "3940775172077954075": {
        "ClientVersion": "5212",
        "ServerVersion": "5212",
        "ProductName": "citadel",
        "appID": "1422450",
        "ServerAppID": "1422460",
        "ToolsAppID": "211",
        "SourceRevision": "9214859",
        "VersionDate": "Sep 26 2024",
        "VersionTime": "23:45:17"
    },
    "5604721781527506154": {
        "ClientVersion": "5213",
        "ServerVersion": "5213",
        "ProductName": "citadel",
        "appID": "1422450",
        "ServerAppID": "1422460",
        "ToolsAppID": "211",
        "SourceRevision": "9215939",
        "VersionDate": "Sep 27 2024",
        "VersionTime": "11:07:08"
    },
    "7228782279719241903": {
        "ClientVersion": "5216",
        "ServerVersion": "5216",
        "ProductName": "citadel",
        "appID": "1422450",
        "ServerAppID": "1422460",
        "ToolsAppID": "211",
        "SourceRevision": "9216633",
        "VersionDate": "Sep 27 2024",
        "VersionTime": "13:36:47"
    },
    "2502515025972263253": {
        "ClientVersion": "5218",
        "ServerVersion": "5218",
        "ProductName": "citadel",
        "appID": "1422450",
        "ServerAppID": "1422460",
        "ToolsAppID": "211",
        "SourceRevision": "9217336",
        "VersionDate": "Sep 27 2024",
        "VersionTime": "16:45:33"
    },
    "7739747708934865940": {
        "ClientVersion": "5219",
        "ServerVersion": "5219",
        "ProductName": "citadel",
        "appID": "1422450",
        "ServerAppID": "1422460",
        "ToolsAppID": "211",
        "SourceRevision": "9217447",
        "VersionDate": "Sep 27 2024",
        "VersionTime": "17:27:44"
    },
    "4177804092237165261": {
        "ClientVersion": "5220",
        "ServerVersion": "5220",
        "ProductName": "citadel",
        "appID": "1422450",
        "ServerAppID": "1422460",
        "ToolsAppID": "211",
        "SourceRevision": "9217762",
        "VersionDate": "Sep 27 2024",
        "VersionTime": "21:14:13"
    },
    "3888703579286624493": {
        "ClientVersion": "5224",
        "ServerVersion": "5224",
        "ProductName": "citadel",
        "appID": "1422450",
        "ServerAppID": "1422460",
        "ToolsAppID": "211",
        "SourceRevision": "9218206",
        "VersionDate": "Sep 29 2024",
        "VersionTime": "12:32:34"
    },
    "1796753196217801764": {
        "ClientVersion": "5226",
        "ServerVersion": "5226",
        "ProductName": "citadel",
        "appID": "1422450",
        "ServerAppID": "1422460",
        "ToolsAppID": "211",
        "SourceRevision": "9219272",
        "VersionDate": "Sep 30 2024",
        "VersionTime": "11:12:14"
    },
    "6377092319738139164": {
        "ClientVersion": "5231",
        "ServerVersion": "5231",
        "ProductName": "citadel",
        "appID": "1422450",
        "ServerAppID": "1422460",
        "ToolsAppID": "211",
        "SourceRevision": "9221276",
        "VersionDate": "Sep 30 2024",
        "VersionTime": "17:11:46"
    },
    "6953839252581323047": {
        "ClientVersion": "5232",
        "ServerVersion": "5232",
        "ProductName": "citadel",
        "appID": "1422450",
        "ServerAppID": "1422460",
        "ToolsAppID": "211",
        "SourceRevision": "9222849",
        "VersionDate": "Oct 01 2024",
        "VersionTime": "10:25:28"
    },
    "6569880859539964512": {
        "ClientVersion": "5233",
        "ServerVersion": "5233",
        "ProductName": "citadel",
        "appID": "1422450",
        "ServerAppID": "1422460",
        "ToolsAppID": "211",
        "SourceRevision": "9223347",
        "VersionDate": "Oct 01 2024",
        "VersionTime": "20:25:15"
    },
    "559689273188132494": {
        "ClientVersion": "5234",
        "ServerVersion": "5234",
        "ProductName": "citadel",
        "appID": "1422450",
        "ServerAppID": "1422460",
        "ToolsAppID": "211",
        "SourceRevision": "9228130",
        "VersionDate": "Oct 02 2024",
        "VersionTime": "17:07:50"
    },
    "7540491025264017760": {
        "ClientVersion": "5235",
        "ServerVersion": "5235",
        "ProductName": "citadel",
        "appID": "1422450",
        "ServerAppID": "1422460",
        "ToolsAppID": "211",
        "SourceRevision": "9233057",
        "VersionDate": "Oct 04 2024",
        "VersionTime": "12:23:38"
    },
    "4597997252167885997": {
        "ClientVersion": "5237",
        "ServerVersion": "5237",
        "ProductName": "citadel",
        "appID": "1422450",
        "ServerAppID": "1422460",
        "ToolsAppID": "211",
        "SourceRevision": "9233588",
        "VersionDate": "Oct 04 2024",
        "VersionTime": "14:11:19"
    },
    "3896233513427826638": {
        "ClientVersion": "5240",
        "ServerVersion": "5240",
        "ProductName": "citadel",
        "appID": "1422450",
        "ServerAppID": "1422460",
        "ToolsAppID": "211",
        "SourceRevision": "9237402",
        "VersionDate": "Oct 07 2024",
        "VersionTime": "12:24:15"
    },
    "2727450184447048827": {
        "ClientVersion": "5247",
        "ServerVersion": "5247",
        "ProductName": "citadel",
        "appID": "1422450",
        "ServerAppID": "1422460",
        "ToolsAppID": "211",
        "SourceRevision": "9248321",
        "VersionDate": "Oct 10 2024",
        "VersionTime": "14:54:49"
    },
    "5777549278038982684": {
        "ClientVersion": "5249",
        "ServerVersion": "5249",
        "ProductName": "citadel",
        "appID": "1422450",
        "ServerAppID": "1422460",
        "ToolsAppID": "211",
        "SourceRevision": "9248633",
        "VersionDate": "Oct 10 2024",
        "VersionTime": "15:49:58"
    },
    "8457411954997566876": {
        "ClientVersion": "5250",
        "ServerVersion": "5250",
        "ProductName": "citadel",
        "appID": "1422450",
        "ServerAppID": "1422460",
        "ToolsAppID": "211",
        "SourceRevision": "9248872",
        "VersionDate": "Oct 10 2024",
        "VersionTime": "16:22:15"
    },
    "3802566217947344592": {
        "ClientVersion": "5251",
        "ServerVersion": "5251",
        "ProductName": "citadel",
        "appID": "1422450",
        "ServerAppID": "1422460",
        "ToolsAppID": "211",
        "SourceRevision": "9249198",
        "VersionDate": "Oct 10 2024",
        "VersionTime": "17:17:35"
    },
    "3208927723092358040": {
        "ClientVersion": "5254",
        "ServerVersion": "5254",
        "ProductName": "citadel",
        "appID": "1422450",
        "ServerAppID": "1422460",
        "ToolsAppID": "211",
        "SourceRevision": "9249522",
        "VersionDate": "Oct 10 2024",
        "VersionTime": "18:35:39"
    },
    "2922445413059759371": {
        "ClientVersion": "5255",
        "ServerVersion": "5255",
        "ProductName": "citadel",
        "appID": "1422450",
        "ServerAppID": "1422460",
        "ToolsAppID": "211",
        "SourceRevision": "9249684",
        "VersionDate": "Oct 10 2024",
        "VersionTime": "19:36:29"
    },
    "6678948280131827378": {
        "ClientVersion": "5257",
        "ServerVersion": "5257",
        "ProductName": "citadel",
        "appID": "1422450",
        "ServerAppID": "1422460",
        "ToolsAppID": "211",
        "SourceRevision": "9250956",
        "VersionDate": "Oct 11 2024",
        "VersionTime": "11:50:26"
    },
    "4493145076681965169": {
        "ClientVersion": "5258",
        "ServerVersion": "5258",
        "ProductName": "citadel",
        "appID": "1422450",
        "ServerAppID": "1422460",
        "ToolsAppID": "211",
        "SourceRevision": "9251495",
        "VersionDate": "Oct 11 2024",
        "VersionTime": "13:37:29"
    },
    "8205479306390334189": {
        "ClientVersion": "5259",
        "ServerVersion": "5259",
        "ProductName": "citadel",
        "appID": "1422450",
        "ServerAppID": "1422460",
        "ToolsAppID": "211",
        "SourceRevision": "9252550",
        "VersionDate": "Oct 11 2024",
        "VersionTime": "16:50:44"
    },
    "2101187347995620337": {
        "ClientVersion": "5260",
        "ServerVersion": "5260",
        "ProductName": "citadel",
        "appID": "1422450",
        "ServerAppID": "1422460",
        "ToolsAppID": "211",
        "SourceRevision": "9253163",
        "VersionDate": "Oct 11 2024",
        "VersionTime": "20:20:48"
    },
    "6059123974617270196": {
        "ClientVersion": "5261",
        "ServerVersion": "5261",
        "ProductName": "citadel",
        "appID": "1422450",
        "ServerAppID": "1422460",
        "ToolsAppID": "211",
        "SourceRevision": "9253708",
        "VersionDate": "Oct 12 2024",
        "VersionTime": "15:29:20"
    },
    "2344015351211296016": {
        "ClientVersion": "5263",
        "ServerVersion": "5263",
        "ProductName": "citadel",
        "appID": "1422450",
        "ServerAppID": "1422460",
        "ToolsAppID": "211",
        "SourceRevision": "9257112",
        "VersionDate": "Oct 14 2024",
        "VersionTime": "18:31:32"
    },
    "6343036909963708404": {
        "ClientVersion": "5265",
        "ServerVersion": "5265",
        "ProductName": "citadel",
        "appID": "1422450",
        "ServerAppID": "1422460",
        "ToolsAppID": "211",
        "SourceRevision": "9257554",
        "VersionDate": "Oct 14 2024",
        "VersionTime": "20:54:52"
    },
    "6222273943798725796": {
        "ClientVersion": "5271",
        "ServerVersion": "5271",
        "ProductName": "citadel",
        "appID": "1422450",
        "ServerAppID": "1422460",
        "ToolsAppID": "211",
        "SourceRevision": "9259174",
        "VersionDate": "Oct 15 2024",
        "VersionTime": "11:40:37"
    },
    "8301626319375826882": {
        "ClientVersion": "5272",
        "ServerVersion": "5272",
        "ProductName": "citadel",
        "appID": "1422450",
        "ServerAppID": "1422460",
        "ToolsAppID": "211",
        "SourceRevision": "9259497",
        "VersionDate": "Oct 15 2024",
        "VersionTime": "12:35:47"
    },
    "8055730768379060909": {
        "ClientVersion": "5273",
        "ServerVersion": "5273",
        "ProductName": "citadel",
        "appID": "1422450",
        "ServerAppID": "1422460",
        "ToolsAppID": "211",
        "SourceRevision": "9261111",
        "VersionDate": "Oct 15 2024",
        "VersionTime": "17:00:24"
    },
    "5199345874697544332": {
        "ClientVersion": "5275",
        "ServerVersion": "5275",
        "ProductName": "citadel",
        "appID": "1422450",
        "ServerAppID": "1422460",
        "ToolsAppID": "211",
        "SourceRevision": "9266925",
        "VersionDate": "Oct 17 2024",
        "VersionTime": "13:38:59"
    },
    "4083897401960189175": {
        "ClientVersion": "5276",
        "ServerVersion": "5276",
        "ProductName": "citadel",
        "appID": "1422450",
        "ServerAppID": "1422460",
        "ToolsAppID": "211",
        "SourceRevision": "9268006",
        "VersionDate": "Oct 17 2024",
        "VersionTime": "16:52:02"
    },
    "5304276363691742940": {
        "ClientVersion": "5277",
        "ServerVersion": "5277",
        "ProductName": "citadel",
        "appID": "1422450",
        "ServerAppID": "1422460",
        "ToolsAppID": "211",
        "SourceRevision": "9269232",
        "VersionDate": "Oct 18 2024",
        "VersionTime": "09:36:39"
    },
    "8044786667015109853": {
        "ClientVersion": "5278",
        "ServerVersion": "5278",
        "ProductName": "citadel",
        "appID": "1422450",
        "ServerAppID": "1422460",
        "ToolsAppID": "211",
        "SourceRevision": "9269680",
        "VersionDate": "Oct 18 2024",
        "VersionTime": "10:55:11"
    },
    "7272722650114169681": {
        "ClientVersion": "5279",
        "ServerVersion": "5279",
        "ProductName": "citadel",
        "appID": "1422450",
        "ServerAppID": "1422460",
        "ToolsAppID": "211",
        "SourceRevision": "9269829",
        "VersionDate": "Oct 18 2024",
        "VersionTime": "11:24:14"
    },
    "7534726504634156525": {
        "ClientVersion": "5280",
        "ServerVersion": "5280",
        "ProductName": "citadel",
        "appID": "1422450",
        "ServerAppID": "1422460",
        "ToolsAppID": "211",
        "SourceRevision": "9270151",
        "VersionDate": "Oct 18 2024",
        "VersionTime": "12:25:19"
    },
    "9028183213409370282": {
        "ClientVersion": "5281",
        "ServerVersion": "5281",
        "ProductName": "citadel",
        "appID": "1422450",
        "ServerAppID": "1422460",
        "ToolsAppID": "211",
        "SourceRevision": "9270203",
        "VersionDate": "Oct 18 2024",
        "VersionTime": "12:42:58"
    },
    "7423908266886961121": {
        "ClientVersion": "5282",
        "ServerVersion": "5282",
        "ProductName": "citadel",
        "appID": "1422450",
        "ServerAppID": "1422460",
        "ToolsAppID": "211",
        "SourceRevision": "9271326",
        "VersionDate": "Oct 18 2024",
        "VersionTime": "16:23:18"
    },
    "2911875555140534363": {
        "ClientVersion": "5284",
        "ServerVersion": "5284",
        "ProductName": "citadel",
        "appID": "1422450",
        "ServerAppID": "1422460",
        "ToolsAppID": "211",
        "SourceRevision": "9273198",
        "VersionDate": "Oct 20 2024",
        "VersionTime": "14:53:40"
    },
    "2446401214387624837": {
        "ClientVersion": "5285",
        "ServerVersion": "5285",
        "ProductName": "citadel",
        "appID": "1422450",
        "ServerAppID": "1422460",
        "ToolsAppID": "211",
        "SourceRevision": "9274070",
        "VersionDate": "Oct 21 2024",
        "VersionTime": "09:39:41"
    },
    "4241662552020026285": {
        "ClientVersion": "5286",
        "ServerVersion": "5286",
        "ProductName": "citadel",
        "appID": "1422450",
        "ServerAppID": "1422460",
        "ToolsAppID": "211",
        "SourceRevision": "9275706",
        "VersionDate": "Oct 21 2024",
        "VersionTime": "14:50:27"
    },
    "7506840751260630350": {
        "ClientVersion": "5289",
        "ServerVersion": "5289",
        "ProductName": "citadel",
        "appID": "1422450",
        "ServerAppID": "1422460",
        "ToolsAppID": "211",
        "SourceRevision": "9278804",
        "VersionDate": "Oct 22 2024",
        "VersionTime": "12:03:34"
    },
    "612899015237309789": {
        "ClientVersion": "5290",
        "ServerVersion": "5290",
        "ProductName": "citadel",
        "appID": "1422450",
        "ServerAppID": "1422460",
        "ToolsAppID": "211",
        "SourceRevision": "9279398",
        "VersionDate": "Oct 22 2024",
        "VersionTime": "13:59:22"
    },
    "7409233371048534330": {
        "ClientVersion": "5291",
        "ServerVersion": "5291",
        "ProductName": "citadel",
        "appID": "1422450",
        "ServerAppID": "1422460",
        "ToolsAppID": "211",
        "SourceRevision": "9280145",
        "VersionDate": "Oct 22 2024",
        "VersionTime": "16:27:37"
    },
    "869927414378704685": {
        "ClientVersion": "5292",
        "ServerVersion": "5292",
        "ProductName": "citadel",
        "appID": "1422450",
        "ServerAppID": "1422460",
        "ToolsAppID": "211",
        "SourceRevision": "9280846",
        "VersionDate": "Oct 22 2024",
        "VersionTime": "18:42:08"
    },
    "4445709161970632714": {
        "ClientVersion": "5293",
        "ServerVersion": "5293",
        "ProductName": "citadel",
        "appID": "1422450",
        "ServerAppID": "1422460",
        "ToolsAppID": "211",
        "SourceRevision": "9281906",
        "VersionDate": "Oct 23 2024",
        "VersionTime": "10:49:10"
    },
    "1220112967339589835": {
        "ClientVersion": "5294",
        "ServerVersion": "5294",
        "ProductName": "citadel",
        "appID": "1422450",
        "ServerAppID": "1422460",
        "ToolsAppID": "211",
        "SourceRevision": "9283470",
        "VersionDate": "Oct 23 2024",
        "VersionTime": "15:42:19"
    },
    "5090297567061318298": {
        "ClientVersion": "5297",
        "ServerVersion": "5297",
        "ProductName": "citadel",
        "appID": "1422450",
        "ServerAppID": "1422460",
        "ToolsAppID": "211",
        "SourceRevision": "9286813",
        "VersionDate": "Oct 24 2024",
        "VersionTime": "13:43:34"
    },
    "4369698927496704222": {
        "ClientVersion": "5298",
        "ServerVersion": "5298",
        "ProductName": "citadel",
        "appID": "1422450",
        "ServerAppID": "1422460",
        "ToolsAppID": "211",
        "SourceRevision": "9287363",
        "VersionDate": "Oct 24 2024",
        "VersionTime": "15:02:34"
    },
    "6902773072939676130": {
        "ClientVersion": "5299",
        "ServerVersion": "5299",
        "ProductName": "citadel",
        "appID": "1422450",
        "ServerAppID": "1422460",
        "ToolsAppID": "211",
        "SourceRevision": "9287538",
        "VersionDate": "Oct 24 2024",
        "VersionTime": "15:32:51"
    },
    "5988645898034166679": {
        "ClientVersion": "5300",
        "ServerVersion": "5300",
        "ProductName": "citadel",
        "appID": "1422450",
        "ServerAppID": "1422460",
        "ToolsAppID": "211",
        "SourceRevision": "9287927",
        "VersionDate": "Oct 24 2024",
        "VersionTime": "16:26:52"
    },
    "597535660973513789": {
        "ClientVersion": "5302",
        "ServerVersion": "5302",
        "ProductName": "citadel",
        "appID": "1422450",
        "ServerAppID": "1422460",
        "ToolsAppID": "211",
        "SourceRevision": "9288502",
        "VersionDate": "Oct 24 2024",
        "VersionTime": "18:02:15"
    },
    "1134822727116852128": {
        "ClientVersion": "5303",
        "ServerVersion": "5303",
        "ProductName": "citadel",
        "appID": "1422450",
        "ServerAppID": "1422460",
        "ToolsAppID": "211",
        "SourceRevision": "9288766",
        "VersionDate": "Oct 24 2024",
        "VersionTime": "19:16:39"
    },
    "6975314021666512244": {
        "ClientVersion": "5304",
        "ServerVersion": "5304",
        "ProductName": "citadel",
        "appID": "1422450",
        "ServerAppID": "1422460",
        "ToolsAppID": "211",
        "SourceRevision": "9289012",
        "VersionDate": "Oct 24 2024",
        "VersionTime": "21:21:11"
    },
    "6711189121801377543": {
        "ClientVersion": "5305",
        "ServerVersion": "5305",
        "ProductName": "citadel",
        "appID": "1422450",
        "ServerAppID": "1422460",
        "ToolsAppID": "211",
        "SourceRevision": "9289088",
        "VersionDate": "Oct 24 2024",
        "VersionTime": "22:33:35"
    },
    "7250810548147076460": {
        "ClientVersion": "5306",
        "ServerVersion": "5306",
        "ProductName": "citadel",
        "appID": "1422450",
        "ServerAppID": "1422460",
        "ToolsAppID": "211",
        "SourceRevision": "9290328",
        "VersionDate": "Oct 25 2024",
        "VersionTime": "11:09:52"
    },
    "1110195483988403873": {
        "ClientVersion": "5307",
        "ServerVersion": "5307",
        "ProductName": "citadel",
        "appID": "1422450",
        "ServerAppID": "1422460",
        "ToolsAppID": "211",
        "SourceRevision": "9290578",
        "VersionDate": "Oct 25 2024",
        "VersionTime": "11:52:32"
    },
    "5868769883342719149": {
        "ClientVersion": "5308",
        "ServerVersion": "5308",
        "ProductName": "citadel",
        "appID": "1422450",
        "ServerAppID": "1422460",
        "ToolsAppID": "211",
        "SourceRevision": "9291788",
        "VersionDate": "Oct 25 2024",
        "VersionTime": "15:33:51"
    },
    "5081198370471146937": {
        "ClientVersion": "5309",
        "ServerVersion": "5309",
        "ProductName": "citadel",
        "appID": "1422450",
        "ServerAppID": "1422460",
        "ToolsAppID": "211",
        "SourceRevision": "9292240",
        "VersionDate": "Oct 25 2024",
        "VersionTime": "17:00:38"
    },
    "6281733434408860619": {
        "ClientVersion": "5310",
        "ServerVersion": "5310",
        "ProductName": "citadel",
        "appID": "1422450",
        "ServerAppID": "1422460",
        "ToolsAppID": "211",
        "SourceRevision": "9292722",
        "VersionDate": "Oct 25 2024",
        "VersionTime": "19:54:16"
    },
    "4092492988322622322": {
        "ClientVersion": "5311",
        "ServerVersion": "5311",
        "ProductName": "citadel",
        "appID": "1422450",
        "ServerAppID": "1422460",
        "ToolsAppID": "211",
        "SourceRevision": "9293308",
        "VersionDate": "Oct 26 2024",
        "VersionTime": "13:35:49"
    }
}